odoo/addons/sale_order_qty_change_no_recompute/README.rst
odoo/addons/sale_order_qty_change_no_recompute/__init__.py
odoo/addons/sale_order_qty_change_no_recompute/__manifest__.py
odoo/addons/sale_order_qty_change_no_recompute/monkeypatching.py
odoo/addons/sale_order_qty_change_no_recompute/i18n/it.po
odoo/addons/sale_order_qty_change_no_recompute/i18n/sale_order_qty_change_no_recompute.pot
odoo/addons/sale_order_qty_change_no_recompute/readme/CONTRIBUTORS.md
odoo/addons/sale_order_qty_change_no_recompute/readme/DESCRIPTION.md
odoo/addons/sale_order_qty_change_no_recompute/readme/ROADMAP.md
odoo/addons/sale_order_qty_change_no_recompute/readme/USAGE.md
odoo/addons/sale_order_qty_change_no_recompute/static/description/icon.png
odoo/addons/sale_order_qty_change_no_recompute/static/description/index.html
odoo/addons/sale_order_qty_change_no_recompute/tests/__init__.py
odoo/addons/sale_order_qty_change_no_recompute/tests/test_sale_order_qty_change.py
odoo_addon_sale_order_qty_change_no_recompute-17.0.1.0.0.2.dist-info/METADATA
odoo_addon_sale_order_qty_change_no_recompute-17.0.1.0.0.2.dist-info/WHEEL
odoo_addon_sale_order_qty_change_no_recompute-17.0.1.0.0.2.dist-info/top_level.txt
odoo_addon_sale_order_qty_change_no_recompute-17.0.1.0.0.2.dist-info/RECORD
